Metadata-Version: 2.1
Name: odoo-addon-l10n_ro_account_bank_statement_import_mt940_bcr
Version: 19.0.0.3.0
Requires-Dist: odoo-addon-l10n_ro_account_bank_statement_import_mt940_base==19.0.*
Requires-Dist: odoo==19.0.*
Summary: MT940 BCR Format Bank Statements Import
Home-page: https://github.com/OCA/l10n-romania
License: AGPL-3
Author: NextERP Romania SRL,Terrabit,Odoo Community Association (OCA)
Author-email: support@odoo-community.org
Classifier: Programming Language :: Python
Classifier: Framework :: Odoo
Classifier: Framework :: Odoo :: 19.0
Classifier: License :: OSI Approved :: GNU Affero General Public License v3
Classifier: Development Status :: 6 - Mature
